pve_cloud_rpc/_version.py
pve_cloud_rpc/server.py
pve_cloud_rpc/protos/cloud_pb2.py
pve_cloud_rpc/protos/cloud_pb2_grpc.py
pve_cloud_rpc/protos/health_pb2.py
pve_cloud_rpc/protos/health_pb2_grpc.py
rpyc_pve_cloud-0.2.5.dist-info/licenses/LICENSE.md
rpyc_pve_cloud-0.2.5.dist-info/METADATA
rpyc_pve_cloud-0.2.5.dist-info/WHEEL
rpyc_pve_cloud-0.2.5.dist-info/entry_points.txt
rpyc_pve_cloud-0.2.5.dist-info/top_level.txt
rpyc_pve_cloud-0.2.5.dist-info/RECORD
