Metadata-Version: 2.4
Name: rpyc-pve-cloud
Version: 0.2.5
Author-email: Tobias Huebner <tobias.huebner@vmzberlin.com>
License-Expression: GPL-3.0-or-later
License-File: LICENSE.md
Requires-Dist: py-pve-cloud<0.16.0,>=0.15.5
Requires-Dist: grpcio==1.76.0
Requires-Dist: asyncssh==2.22.0
Requires-Dist: protobuf==6.33.4
Dynamic: license-file
